adcm_aio_client/__init__.py
adcm_aio_client/_filters.py
adcm_aio_client/_session.py
adcm_aio_client/_types.py
adcm_aio_client/_utils.py
adcm_aio_client/actions/__init__.py
adcm_aio_client/actions/_objects.py
adcm_aio_client/client.py
adcm_aio_client/config/__init__.py
adcm_aio_client/config/_objects.py
adcm_aio_client/config/_operations.py
adcm_aio_client/config/_refresh.py
adcm_aio_client/config/_types.py
adcm_aio_client/errors.py
adcm_aio_client/host_groups/__init__.py
adcm_aio_client/host_groups/_action_group.py
adcm_aio_client/host_groups/_common.py
adcm_aio_client/host_groups/_config_group.py
adcm_aio_client/mapping/__init__.py
adcm_aio_client/mapping/_objects.py
adcm_aio_client/mapping/_refresh.py
adcm_aio_client/mapping/_types.py
adcm_aio_client/objects/__init__.py
adcm_aio_client/objects/_accessors.py
adcm_aio_client/objects/_base.py
adcm_aio_client/objects/_cm.py
adcm_aio_client/objects/_common.py
adcm_aio_client/objects/_imports.py
adcm_aio_client/requesters.py
adcm_aio_client-0.1.1.dist-info/LICENSE
adcm_aio_client-0.1.1.dist-info/METADATA
adcm_aio_client-0.1.1.dist-info/WHEEL
adcm_aio_client-0.1.1.dist-info/RECORD
