Metadata-Version: 2.3
Name: adcm-aio-client
Version: 0.1.1
Summary: Asynchronous HTTP Client for ADCM (Arenadata Cluster Manager)
License: Apache-2.0
Keywords: ADCM
Author: Aleksandr Alferov
Author-email: <aas@arenadata.io>
Requires-Python: >=3.12
Classifier: Development Status :: 3 - Alpha
Classifier: License :: OSI Approved :: Apache Software License
Classifier: Programming Language :: Python :: 3
Classifier: Programming Language :: Python :: 3.12
Classifier: Programming Language :: Python :: 3.13
Classifier: Topic :: Software Development :: Build Tools
Classifier: Topic :: Software Development :: Libraries :: Python Modules
Requires-Dist: adcm-version (>=1.0.3,<2.0.0)
Requires-Dist: asyncstdlib (>=3.13.0,<4.0.0)
Requires-Dist: httpx (>=0.27.2,<1.0.0)
Project-URL: Homepage, https://github.com/arenadata/adcm-aio-client
Project-URL: Repository, https://github.com/arenadata/adcm-aio-client
